setup.py
demo/__init__.py
my777demo.egg-info/PKG-INFO
my777demo.egg-info/SOURCES.txt
my777demo.egg-info/dependency_links.txt
my777demo.egg-info/top_level.txt