Metadata-Version: 1.0
Name: my777demo
Version: 1.0
Summary: this is a test
Home-page: https://www.test.com
Author: JFU
Author-email: test@qq.com
License: UNKNOWN
Platform: UNKNOWN
